README.md
setup.py
nest_redis.egg-info/PKG-INFO
nest_redis.egg-info/SOURCES.txt
nest_redis.egg-info/dependency_links.txt
nest_redis.egg-info/requires.txt
nest_redis.egg-info/top_level.txt
pyredis/__init__.py
pyredis/cache.py